persist_sql/__init__.py
persist_sql-0.2.1.dist-info/METADATA
persist_sql-0.2.1.dist-info/WHEEL
persist_sql-0.2.1.dist-info/top_level.txt
persist_sql-0.2.1.dist-info/RECORD
