Metadata-Version: 2.4
Name: persist_sql
Version: 0.2.1
Summary: Peristent SQLite Database using S3 on Cloud Workspaces
Author-email: Siddharth Singh <siddharthsingh5010@icloud.com>
Requires-Python: >=3.6
Requires-Dist: boto3
Requires-Dist: pandas
Requires-Dist: numpy
